py_astrolab/__init__.py
py_astrolab/aspects.py
py_astrolab/charts/__init__.py
py_astrolab/charts/charts_svg.py
py_astrolab/charts/templates/basic.xml
py_astrolab/charts/templates/extended.xml
py_astrolab/charts/templates/minimal.xml
py_astrolab/charts/wonderful_mistake.py
py_astrolab/fetch_geonames.py
py_astrolab/kr.config.json
py_astrolab/main.py
py_astrolab/print_all_data.py
py_astrolab/relationship_score.py
py_astrolab/report.py
py_astrolab/transits.py
py_astrolab/types.py
py_astrolab/utilities.py
py_astrolab-0.16.1.dist-info/METADATA
py_astrolab-0.16.1.dist-info/WHEEL
py_astrolab-0.16.1.dist-info/RECORD
