Metadata-Version: 2.1
Name: py-astrolab
Version: 0.16.1
Summary: A Python interface on Swiss Ephemeris to perform astrological calculations
License: GNU General Public License (GPL)
Author: Giacomo Battaglia
Author-email: battaglia.giacomo@yahoo.it
Requires-Python: >=3.9,<3.10
Classifier: License :: Other/Proprietary License
Classifier: Programming Language :: Python :: 3
Classifier: Programming Language :: Python :: 3.9
Requires-Dist: jsonpickle (==1.4.2)
Requires-Dist: pdoc
Requires-Dist: pydantic
Requires-Dist: pyswisseph (==2.8.0.post1)
Requires-Dist: pytest
Requires-Dist: pytz (>=2022.7)
Requires-Dist: requests (==2.31.0)
Requires-Dist: requests-cache (==0.9.3)
Requires-Dist: terminaltables
